ajwt/__init__.py
ajwt/config.py
ajwt/jwt_parser.py
ajwt/jwt_tool.py
ajwt/py.typed
ajwt/rsa_tool.py
ajwt-0.2.2.dist-info/WHEEL
ajwt-0.2.2.dist-info/entry_points.txt
ajwt-0.2.2.dist-info/METADATA
ajwt-0.2.2.dist-info/RECORD
