Metadata-Version: 2.3
Name: ajwt
Version: 0.2.2
Summary: Add your description here
Author: wmymz
Author-email: wmymz <wmymz@icloud.com>
Requires-Dist: crypto-plus>=1.0.6
Requires-Dist: gmpy2>=2.2.1
Requires-Python: >=3.7, <3.14
